{
    "home": {
        "buttons": [
            {
                "name": "play",
                "rect": [
                    260,
                    362,
                    200,
                    75
                ],
                "color": [
                    0,
                    100,
                    0
                ],
                "text": "PLAY",
                "text_color": [
                    0,
                    0,
                    0
                ],
                "padding": 5,
                "callback": "set_game_state_setup"
            },
            {
                "name": "quit",
                "rect": [
                    260,
                    444,
                    200,
                    75
                ],
                "color": [
                    100,
                    0,
                    0
                ],
                "text": "QUIT",
                "text_color": [
                    0,
                    0,
                    0
                ],
                "padding": 5,
                "callback": "quit"
            }
        ],
        "images": [],
        "sliders": [],
        "toggles": [],
        "text_displays": [],
        "scrollable_areas": [],
        "text_inputs": [],
        "multi_selects": [],
        "menus": [
            "settings"
        ]
    },
    "setup": {
        "buttons": [
            {
                "name": "difficulty_level_easy",
                "rect": [
                    282,
                    71,
                    75,
                    30
                ],
                "color": [
                    0,
                    0,
                    0
                ],
                "text": "easy",
                "text_color": [
                    255,
                    255,
                    255
                ],
                "padding": 5,
                "callback": "set_diff_level_easy"
            },
            {
                "name": "difficulty_level_medium",
                "rect": [
                    382,
                    71,
                    75,
                    30
                ],
                "color": [
                    0,
                    0,
                    0
                ],
                "text": "medium",
                "text_color": [
                    255,
                    255,
                    255
                ],
                "padding": 5,
                "callback": "set_diff_level_medium"
            },
            {
                "name": "difficulty_level_hard",
                "rect": [
                    490,
                    69,
                    70,
                    30
                ],
                "color": [
                    0,
                    0,
                    0
                ],
                "text": "hard",
                "text_color": [
                    255,
                    255,
                    255
                ],
                "padding": 5,
                "callback": "set_diff_level_hard"
            },
            {
                "name": "open_menu",
                "rect": [
                    1268,
                    21,
                    75,
                    75
                ],
                "color": [
                    100,
                    0,
                    0
                ],
                "text": "image",
                "text_color": [
                    0,
                    0,
                    0
                ],
                "padding": 5,
                "callback": "open_menu"
            },
            {
                "name": "player_choose_color_cycle",
                "rect": [
                    654,
                    87,
                    20,
                    20
                ],
                "color": [
                    0,
                    0,
                    0
                ],
                "text": "->",
                "text_color": [
                    0,
                    0,
                    0
                ],
                "padding": 5,
                "callback": "choose_player_color_cycle"
            },
            {
                "name": "game_start",
                "rect": [
                    949,
                    576,
                    150,
                    50
                ],
                "color": [
                    100,
                    0,
                    0
                ],
                "text": "Start",
                "text_color": [
                    0,
                    0,
                    0
                ],
                "padding": 5,
                "callback": "start_game"
            },
            {
                "name": "game_setup_back",
                "rect": [
                    229,
                    384,
                    50,
                    30
                ],
                "color": [
                    100,
                    0,
                    0
                ],
                "text": "Back",
                "text_color": [
                    0,
                    0,
                    0
                ],
                "padding": 5,
                "callback": "set_game_state_home"
            }
        ],
        "images": [],
        "sliders": [
            {
                "name": "player_num_slider",
                "rect": [
                    100,
                    200,
                    300,
                    20
                ],
                "min_value": 1,
                "max_value": 4,
                "color": [
                    0,
                    100,
                    0
                ],
                "handle_color": [
                    100,
                    0,
                    0
                ],
                "handle_radius": 10
            }
        ],
        "toggles": [],
        "text_displays": [
            {
                "name": "player_num_text",
                "rect": [
                    100,
                    150,
                    300,
                    50
                ],
                "color": [
                    255,
                    255,
                    255
                ],
                "text": "Number of Players: 1",
                "text_color": [
                    0,
                    0,
                    0
                ],
                "padding": 5
            }
        ],
        "scrollable_areas": [
            {
                "name": "test_scrollable",
                "rect": [
                    816,
                    67,
                    300,
                    400
                ],
                "guiding_line_color": [
                    100,
                    100,
                    200
                ],
                "_type": "ScrollableArea",
                "slider_layout_props": {
                    "name": "slider",
                    "rect": [
                        266,
                        5,
                        29,
                        390
                    ],
                    "guiding_line_color": [
                        100,
                        100,
                        200
                    ],
                    "_type": "Slider",
                    "value": 0,
                    "min_value": 0,
                    "max_value": 1,
                    "color": [
                        0,
                        100,
                        0
                    ],
                    "handle_color": [
                        50,
                        50,
                        200
                    ],
                    "handle_radius": 12,
                    "direction": "vertical",
                    "handle_shape": "circle",
                    "handle_length": 20
                },
                "exterior_padding": 5,
                "interior_padding": 5,
                "viewable_content_height": 390,
                "viewable_content_width": 256,
                "background_color": [
                    200,
                    200,
                    200,
                    255
                ],
                "content_background_color": [
                    255,
                    255,
                    255,
                    255
                ],
                "slider_side": "right",
                "content_width_percentage": 0.9
            }
        ],
        "text_inputs": [],
        "multi_selects": [],
        "menus": [
            "settings"
        ]
    },
    "game": {
        "buttons": [
            {
                "name": "board_buy_settlement",
                "rect": [
                    700,
                    650,
                    40,
                    40
                ],
                "color": [
                    0,
                    0,
                    0
                ],
                "text": "image",
                "text_color": [
                    0,
                    0,
                    0
                ],
                "padding": 5
            },
            {
                "name": "board_buy_city",
                "rect": [
                    800,
                    650,
                    40,
                    40
                ],
                "color": [
                    0,
                    0,
                    0
                ],
                "text": "image",
                "text_color": [
                    0,
                    0,
                    0
                ],
                "padding": 5
            },
            {
                "name": "board_buy_road",
                "rect": [
                    900,
                    10,
                    10,
                    40
                ],
                "color": [
                    0,
                    0,
                    0
                ],
                "text": "image",
                "text_color": [
                    0,
                    0,
                    0
                ],
                "padding": 5
            },
            {
                "name": "board_buy_development",
                "rect": [
                    1000,
                    40,
                    40,
                    40
                ],
                "color": [
                    0,
                    0,
                    0
                ],
                "text": "image",
                "text_color": [
                    0,
                    0,
                    0
                ],
                "padding": 5
            },
            {
                "name": "board_roll_dice",
                "rect": [
                    1050,
                    600,
                    40,
                    40
                ],
                "color": [
                    0,
                    0,
                    0
                ],
                "text": "image",
                "text_color": [
                    0,
                    0,
                    0
                ],
                "padding": 5
            },
            {
                "name": "settings_menu",
                "rect": [
                    1268,
                    21,
                    75,
                    75
                ],
                "color": [
                    100,
                    0,
                    0
                ],
                "text": "image",
                "text_color": [
                    0,
                    0,
                    0
                ],
                "padding": 5,
                "callback": "open_menu"
            },
            {
                "name": "back",
                "rect": [
                    10,
                    10,
                    70,
                    40
                ],
                "color": [
                    100,
                    100,
                    200
                ],
                "text": "back",
                "text_color": [
                    0,
                    0,
                    0
                ],
                "padding": 5,
                "callback": "set_game_state_home"
            }
        ],
        "images": [],
        "sliders": [],
        "toggles": [],
        "text_displays": [],
        "scrollable_areas": [],
        "text_inputs": [],
        "multi_selects": [],
        "menus": [
            "settings"
        ]
    },
    "menus": [
        {
            "name": "settings",
            "rect": [
                -201,
                -158,
                1346,
                780
            ],
            "guiding_line_color": [
                100,
                100,
                200
            ],
            "children": [
                "input",
                "accessibility",
                "gameplay",
                "audio",
                "graphics",
                "close_menu",
                "test3",
                "aa",
                "fullscreen",
                "shadows",
                "brightness",
                "test3",
                "aa",
                "fullscreen",
                "shadows",
                "brightness",
                "test3",
                "aa",
                "fullscreen",
                "shadows",
                "brightness",
                "test3",
                "aa",
                "fullscreen",
                "shadows",
                "brightness",
                "test3",
                "aa",
                "fullscreen",
                "shadows",
                "brightness",
                "new_button_41038",
                "new_toggle_69459",
                "new_slider_93487"
            ],
            "_type": "Menu",
            "bckg_color": [
                100,
                100,
                100
            ],
            "init_location": [
                9,
                11
            ],
            "final_location": [
                9,
                11
            ],
            "anim_length": 0.5,
            "active_tab": "input",
            "tabs": [
                "input",
                "accessibility",
                "gameplay",
                "audio",
                "graphics"
            ],
            "z_index": 0,
            "exclusive_with": [],
            "modal": false,
            "close_on_state_change": true,
            "buttons": {
                "tabs": {
                    "input": {
                        "name": "input",
                        "rect": [
                            300,
                            20,
                            60,
                            35
                        ],
                        "guiding_line_color": [
                            100,
                            100,
                            200
                        ],
                        "_type": "Button",
                        "color": [
                            0,
                            100,
                            0
                        ],
                        "text_align": "center",
                        "text": "Input",
                        "shown": true,
                        "padding": 5,
                        "text_color": [
                            0,
                            0,
                            0
                        ],
                        "border_radius": 0,
                        "border_top_right_radius": 0,
                        "border_top_left_radius": 0,
                        "border_bottom_right_radius": 0,
                        "border_bottom_left_radius": 0,
                        "callback": "change_tab_input"
                    },
                    "accessibility": {
                        "name": "accessibility",
                        "rect": [
                            396,
                            19,
                            130,
                            35
                        ],
                        "guiding_line_color": [
                            100,
                            100,
                            200
                        ],
                        "_type": "Button",
                        "color": [
                            100,
                            0,
                            0
                        ],
                        "text_align": "center",
                        "text": "Accessibility",
                        "shown": true,
                        "padding": 5,
                        "text_color": [
                            0,
                            0,
                            0
                        ],
                        "border_radius": 0,
                        "border_top_right_radius": 0,
                        "border_top_left_radius": 0,
                        "border_bottom_right_radius": 0,
                        "border_bottom_left_radius": 0,
                        "callback": "change_tab_accessibility"
                    },
                    "gameplay": {
                        "name": "gameplay",
                        "rect": [
                            566,
                            19,
                            95,
                            35
                        ],
                        "guiding_line_color": [
                            100,
                            100,
                            200
                        ],
                        "_type": "Button",
                        "color": [
                            100,
                            0,
                            0
                        ],
                        "text_align": "center",
                        "text": "Gameplay",
                        "shown": true,
                        "padding": 5,
                        "text_color": [
                            0,
                            0,
                            0
                        ],
                        "border_radius": 0,
                        "border_top_right_radius": 0,
                        "border_top_left_radius": 0,
                        "border_bottom_right_radius": 0,
                        "border_bottom_left_radius": 0,
                        "callback": "change_tab_gameplay"
                    },
                    "audio": {
                        "name": "audio",
                        "rect": [
                            700,
                            20,
                            65,
                            35
                        ],
                        "guiding_line_color": [
                            100,
                            100,
                            200
                        ],
                        "_type": "Button",
                        "color": [
                            100,
                            0,
                            0
                        ],
                        "text_align": "center",
                        "text": "Audio",
                        "shown": true,
                        "padding": 5,
                        "text_color": [
                            0,
                            0,
                            0
                        ],
                        "border_radius": 0,
                        "border_top_right_radius": 0,
                        "border_top_left_radius": 0,
                        "border_bottom_right_radius": 0,
                        "border_bottom_left_radius": 0,
                        "callback": "change_tab_audio"
                    },
                    "graphics": {
                        "name": "graphics",
                        "rect": [
                            800,
                            20,
                            90,
                            35
                        ],
                        "guiding_line_color": [
                            100,
                            100,
                            200
                        ],
                        "_type": "Button",
                        "color": [
                            100,
                            0,
                            0
                        ],
                        "text_align": "center",
                        "text": "Graphics",
                        "shown": true,
                        "padding": 5,
                        "text_color": [
                            0,
                            0,
                            0
                        ],
                        "border_radius": 0,
                        "border_top_right_radius": 0,
                        "border_top_left_radius": 0,
                        "border_bottom_right_radius": 0,
                        "border_bottom_left_radius": 0,
                        "callback": "change_tab_graphics"
                    },
                    "close_menu": {
                        "name": "close_menu",
                        "rect": [
                            1116,
                            50,
                            100,
                            50
                        ],
                        "guiding_line_color": [
                            100,
                            100,
                            200
                        ],
                        "_type": "Button",
                        "color": [
                            100,
                            0,
                            0
                        ],
                        "text_align": "center",
                        "text": "Close",
                        "shown": true,
                        "padding": 5,
                        "text_color": [
                            0,
                            0,
                            0
                        ],
                        "border_radius": 0,
                        "border_top_right_radius": 0,
                        "border_top_left_radius": 0,
                        "border_bottom_right_radius": 0,
                        "border_bottom_left_radius": 0,
                        "callback": "close_menu"
                    }
                },
                "input": {
                    "test3": {
                        "name": "test3",
                        "rect": [
                            275,
                            105,
                            100,
                            50
                        ],
                        "guiding_line_color": [
                            100,
                            100,
                            200
                        ],
                        "_type": "Button",
                        "color": [
                            200,
                            50,
                            100
                        ],
                        "text_align": "center",
                        "text": "1",
                        "shown": true,
                        "padding": 5,
                        "text_color": [
                            0,
                            0,
                            0
                        ],
                        "border_radius": 0,
                        "border_top_right_radius": 0,
                        "border_top_left_radius": 0,
                        "border_bottom_right_radius": 0,
                        "border_bottom_left_radius": 0
                    },
                    "new_button_41038": {
                        "name": "new_button_41038",
                        "rect": [
                            649,
                            210,
                            150,
                            50
                        ],
                        "guiding_line_color": [
                            100,
                            100,
                            200
                        ],
                        "_type": "Button",
                        "color": [
                            0,
                            100,
                            0
                        ],
                        "text_align": "center",
                        "text": "new button",
                        "shown": true,
                        "padding": 5,
                        "text_color": [
                            0,
                            0,
                            0
                        ],
                        "border_radius": 0,
                        "border_top_right_radius": 0,
                        "border_top_left_radius": 0,
                        "border_bottom_right_radius": 0,
                        "border_bottom_left_radius": 0
                    }
                },
                "accessibility": {
                    "test3": {
                        "name": "test3",
                        "rect": [
                            275,
                            105,
                            100,
                            50
                        ],
                        "guiding_line_color": [
                            100,
                            100,
                            200
                        ],
                        "_type": "Button",
                        "color": [
                            200,
                            50,
                            100
                        ],
                        "text_align": "center",
                        "text": "4",
                        "shown": false,
                        "padding": 5,
                        "text_color": [
                            0,
                            0,
                            0
                        ],
                        "border_radius": 0,
                        "border_top_right_radius": 0,
                        "border_top_left_radius": 0,
                        "border_bottom_right_radius": 0,
                        "border_bottom_left_radius": 0
                    }
                },
                "graphics": {
                    "test3": {
                        "name": "test3",
                        "rect": [
                            275,
                            105,
                            100,
                            50
                        ],
                        "guiding_line_color": [
                            100,
                            100,
                            200
                        ],
                        "_type": "Button",
                        "color": [
                            200,
                            50,
                            100
                        ],
                        "text_align": "center",
                        "text": "4",
                        "shown": false,
                        "padding": 5,
                        "text_color": [
                            0,
                            0,
                            0
                        ],
                        "border_radius": 0,
                        "border_top_right_radius": 0,
                        "border_top_left_radius": 0,
                        "border_bottom_right_radius": 0,
                        "border_bottom_left_radius": 0
                    }
                },
                "audio": {
                    "test3": {
                        "name": "test3",
                        "rect": [
                            275,
                            105,
                            100,
                            50
                        ],
                        "guiding_line_color": [
                            100,
                            100,
                            200
                        ],
                        "_type": "Button",
                        "color": [
                            200,
                            50,
                            100
                        ],
                        "text_align": "center",
                        "text": "4",
                        "shown": false,
                        "padding": 5,
                        "text_color": [
                            0,
                            0,
                            0
                        ],
                        "border_radius": 0,
                        "border_top_right_radius": 0,
                        "border_top_left_radius": 0,
                        "border_bottom_right_radius": 0,
                        "border_bottom_left_radius": 0
                    }
                },
                "gameplay": {
                    "test3": {
                        "name": "test3",
                        "rect": [
                            275,
                            105,
                            100,
                            50
                        ],
                        "guiding_line_color": [
                            100,
                            100,
                            200
                        ],
                        "_type": "Button",
                        "color": [
                            200,
                            50,
                            100
                        ],
                        "text_align": "center",
                        "text": "4",
                        "shown": false,
                        "padding": 5,
                        "text_color": [
                            0,
                            0,
                            0
                        ],
                        "border_radius": 0,
                        "border_top_right_radius": 0,
                        "border_top_left_radius": 0,
                        "border_bottom_right_radius": 0,
                        "border_bottom_left_radius": 0
                    }
                }
            },
            "toggles": {
                "tabs": {},
                "input": {
                    "aa": {
                        "name": "aa",
                        "rect": [
                            200,
                            300,
                            150,
                            50
                        ],
                        "guiding_line_color": [
                            100,
                            100,
                            200
                        ],
                        "_type": "Toggle",
                        "on": false,
                        "guiding_lines": true,
                        "height": 50,
                        "center_width": 100,
                        "color": [
                            0,
                            100,
                            0
                        ],
                        "handle_color": [
                            100,
                            0,
                            0
                        ],
                        "toggle_gap": 7,
                        "time_to_flip": 0.25
                    },
                    "fullscreen": {
                        "name": "fullscreen",
                        "rect": [
                            300,
                            300,
                            150,
                            50
                        ],
                        "guiding_line_color": [
                            100,
                            100,
                            200
                        ],
                        "_type": "Toggle",
                        "on": false,
                        "guiding_lines": true,
                        "height": 50,
                        "center_width": 100,
                        "color": [
                            0,
                            100,
                            0
                        ],
                        "handle_color": [
                            100,
                            0,
                            0
                        ],
                        "toggle_gap": 7,
                        "time_to_flip": 0.25
                    },
                    "shadows": {
                        "name": "shadows",
                        "rect": [
                            400,
                            300,
                            150,
                            50
                        ],
                        "guiding_line_color": [
                            100,
                            100,
                            200
                        ],
                        "_type": "Toggle",
                        "on": false,
                        "guiding_lines": true,
                        "height": 50,
                        "center_width": 100,
                        "color": [
                            0,
                            100,
                            0
                        ],
                        "handle_color": [
                            100,
                            0,
                            0
                        ],
                        "toggle_gap": 7,
                        "time_to_flip": 0.25
                    },
                    "new_toggle_69459": {
                        "name": "new_toggle_69459",
                        "rect": [
                            645,
                            270,
                            150,
                            50
                        ],
                        "guiding_line_color": [
                            100,
                            100,
                            200
                        ],
                        "_type": "Toggle",
                        "on": false,
                        "guiding_lines": true,
                        "height": 50,
                        "center_width": 100,
                        "color": [
                            0,
                            100,
                            0
                        ],
                        "handle_color": [
                            100,
                            0,
                            0
                        ],
                        "toggle_gap": 7,
                        "time_to_flip": 0.25
                    }
                },
                "accessibility": {
                    "aa": {
                        "name": "aa",
                        "rect": [
                            200,
                            300,
                            150,
                            50
                        ],
                        "guiding_line_color": [
                            100,
                            100,
                            200
                        ],
                        "_type": "Toggle",
                        "on": false,
                        "guiding_lines": true,
                        "height": 50,
                        "center_width": 100,
                        "color": [
                            0,
                            100,
                            0
                        ],
                        "handle_color": [
                            100,
                            0,
                            0
                        ],
                        "toggle_gap": 7,
                        "time_to_flip": 0.25
                    },
                    "fullscreen": {
                        "name": "fullscreen",
                        "rect": [
                            300,
                            300,
                            150,
                            50
                        ],
                        "guiding_line_color": [
                            100,
                            100,
                            200
                        ],
                        "_type": "Toggle",
                        "on": false,
                        "guiding_lines": true,
                        "height": 50,
                        "center_width": 100,
                        "color": [
                            0,
                            100,
                            0
                        ],
                        "handle_color": [
                            100,
                            0,
                            0
                        ],
                        "toggle_gap": 7,
                        "time_to_flip": 0.25
                    },
                    "shadows": {
                        "name": "shadows",
                        "rect": [
                            400,
                            300,
                            150,
                            50
                        ],
                        "guiding_line_color": [
                            100,
                            100,
                            200
                        ],
                        "_type": "Toggle",
                        "on": false,
                        "guiding_lines": true,
                        "height": 50,
                        "center_width": 100,
                        "color": [
                            0,
                            100,
                            0
                        ],
                        "handle_color": [
                            100,
                            0,
                            0
                        ],
                        "toggle_gap": 7,
                        "time_to_flip": 0.25
                    }
                },
                "graphics": {
                    "aa": {
                        "name": "aa",
                        "rect": [
                            200,
                            300,
                            150,
                            50
                        ],
                        "guiding_line_color": [
                            100,
                            100,
                            200
                        ],
                        "_type": "Toggle",
                        "on": false,
                        "guiding_lines": true,
                        "height": 50,
                        "center_width": 100,
                        "color": [
                            0,
                            100,
                            0
                        ],
                        "handle_color": [
                            100,
                            0,
                            0
                        ],
                        "toggle_gap": 7,
                        "time_to_flip": 0.25
                    },
                    "fullscreen": {
                        "name": "fullscreen",
                        "rect": [
                            300,
                            300,
                            150,
                            50
                        ],
                        "guiding_line_color": [
                            100,
                            100,
                            200
                        ],
                        "_type": "Toggle",
                        "on": false,
                        "guiding_lines": true,
                        "height": 50,
                        "center_width": 100,
                        "color": [
                            0,
                            100,
                            0
                        ],
                        "handle_color": [
                            100,
                            0,
                            0
                        ],
                        "toggle_gap": 7,
                        "time_to_flip": 0.25
                    },
                    "shadows": {
                        "name": "shadows",
                        "rect": [
                            400,
                            300,
                            150,
                            50
                        ],
                        "guiding_line_color": [
                            100,
                            100,
                            200
                        ],
                        "_type": "Toggle",
                        "on": false,
                        "guiding_lines": true,
                        "height": 50,
                        "center_width": 100,
                        "color": [
                            0,
                            100,
                            0
                        ],
                        "handle_color": [
                            100,
                            0,
                            0
                        ],
                        "toggle_gap": 7,
                        "time_to_flip": 0.25
                    }
                },
                "audio": {
                    "aa": {
                        "name": "aa",
                        "rect": [
                            200,
                            300,
                            150,
                            50
                        ],
                        "guiding_line_color": [
                            100,
                            100,
                            200
                        ],
                        "_type": "Toggle",
                        "on": false,
                        "guiding_lines": true,
                        "height": 50,
                        "center_width": 100,
                        "color": [
                            0,
                            100,
                            0
                        ],
                        "handle_color": [
                            100,
                            0,
                            0
                        ],
                        "toggle_gap": 7,
                        "time_to_flip": 0.25
                    },
                    "fullscreen": {
                        "name": "fullscreen",
                        "rect": [
                            300,
                            300,
                            150,
                            50
                        ],
                        "guiding_line_color": [
                            100,
                            100,
                            200
                        ],
                        "_type": "Toggle",
                        "on": false,
                        "guiding_lines": true,
                        "height": 50,
                        "center_width": 100,
                        "color": [
                            0,
                            100,
                            0
                        ],
                        "handle_color": [
                            100,
                            0,
                            0
                        ],
                        "toggle_gap": 7,
                        "time_to_flip": 0.25
                    },
                    "shadows": {
                        "name": "shadows",
                        "rect": [
                            400,
                            300,
                            150,
                            50
                        ],
                        "guiding_line_color": [
                            100,
                            100,
                            200
                        ],
                        "_type": "Toggle",
                        "on": false,
                        "guiding_lines": true,
                        "height": 50,
                        "center_width": 100,
                        "color": [
                            0,
                            100,
                            0
                        ],
                        "handle_color": [
                            100,
                            0,
                            0
                        ],
                        "toggle_gap": 7,
                        "time_to_flip": 0.25
                    }
                },
                "gameplay": {
                    "aa": {
                        "name": "aa",
                        "rect": [
                            200,
                            300,
                            150,
                            50
                        ],
                        "guiding_line_color": [
                            100,
                            100,
                            200
                        ],
                        "_type": "Toggle",
                        "on": false,
                        "guiding_lines": true,
                        "height": 50,
                        "center_width": 100,
                        "color": [
                            0,
                            100,
                            0
                        ],
                        "handle_color": [
                            100,
                            0,
                            0
                        ],
                        "toggle_gap": 7,
                        "time_to_flip": 0.25
                    },
                    "fullscreen": {
                        "name": "fullscreen",
                        "rect": [
                            300,
                            300,
                            150,
                            50
                        ],
                        "guiding_line_color": [
                            100,
                            100,
                            200
                        ],
                        "_type": "Toggle",
                        "on": false,
                        "guiding_lines": true,
                        "height": 50,
                        "center_width": 100,
                        "color": [
                            0,
                            100,
                            0
                        ],
                        "handle_color": [
                            100,
                            0,
                            0
                        ],
                        "toggle_gap": 7,
                        "time_to_flip": 0.25
                    },
                    "shadows": {
                        "name": "shadows",
                        "rect": [
                            400,
                            300,
                            150,
                            50
                        ],
                        "guiding_line_color": [
                            100,
                            100,
                            200
                        ],
                        "_type": "Toggle",
                        "on": false,
                        "guiding_lines": true,
                        "height": 50,
                        "center_width": 100,
                        "color": [
                            0,
                            100,
                            0
                        ],
                        "handle_color": [
                            100,
                            0,
                            0
                        ],
                        "toggle_gap": 7,
                        "time_to_flip": 0.25
                    }
                }
            },
            "sliders": {
                "tabs": {},
                "input": {
                    "brightness": {
                        "name": "brightness",
                        "rect": [
                            100,
                            200,
                            300,
                            20
                        ],
                        "guiding_line_color": [
                            100,
                            100,
                            200
                        ],
                        "_type": "Slider",
                        "value": 0.3535714285714286,
                        "min_value": 0,
                        "max_value": 1,
                        "color": [
                            0,
                            100,
                            0
                        ],
                        "handle_color": [
                            100,
                            0,
                            0
                        ],
                        "handle_radius": 10,
                        "direction": "horizontal",
                        "handle_shape": "circle",
                        "handle_length": 0
                    },
                    "new_slider_93487": {
                        "name": "new_slider_93487",
                        "rect": [
                            100,
                            100,
                            200,
                            40
                        ],
                        "guiding_line_color": [
                            100,
                            100,
                            200
                        ],
                        "_type": "Slider",
                        "value": 46.25,
                        "min_value": 0,
                        "max_value": 100,
                        "color": [
                            100,
                            0,
                            0
                        ],
                        "handle_color": [
                            200,
                            200,
                            200
                        ],
                        "handle_radius": 10,
                        "direction": "horizontal",
                        "handle_shape": "circle",
                        "handle_length": 0
                    }
                },
                "accessibility": {
                    "brightness": {
                        "name": "brightness",
                        "rect": [
                            100,
                            200,
                            300,
                            20
                        ],
                        "guiding_line_color": [
                            100,
                            100,
                            200
                        ],
                        "_type": "Slider",
                        "value": 0,
                        "min_value": 0,
                        "max_value": 1,
                        "color": [
                            0,
                            100,
                            0
                        ],
                        "handle_color": [
                            100,
                            0,
                            0
                        ],
                        "handle_radius": 10,
                        "direction": "horizontal",
                        "handle_shape": "circle",
                        "handle_length": 0
                    }
                },
                "graphics": {
                    "brightness": {
                        "name": "brightness",
                        "rect": [
                            100,
                            200,
                            300,
                            20
                        ],
                        "guiding_line_color": [
                            100,
                            100,
                            200
                        ],
                        "_type": "Slider",
                        "value": 0,
                        "min_value": 0,
                        "max_value": 1,
                        "color": [
                            0,
                            100,
                            0
                        ],
                        "handle_color": [
                            100,
                            0,
                            0
                        ],
                        "handle_radius": 10,
                        "direction": "horizontal",
                        "handle_shape": "circle",
                        "handle_length": 0
                    }
                },
                "audio": {
                    "brightness": {
                        "name": "brightness",
                        "rect": [
                            100,
                            200,
                            300,
                            20
                        ],
                        "guiding_line_color": [
                            100,
                            100,
                            200
                        ],
                        "_type": "Slider",
                        "value": 0,
                        "min_value": 0,
                        "max_value": 1,
                        "color": [
                            0,
                            100,
                            0
                        ],
                        "handle_color": [
                            100,
                            0,
                            0
                        ],
                        "handle_radius": 10,
                        "direction": "horizontal",
                        "handle_shape": "circle",
                        "handle_length": 0
                    }
                },
                "gameplay": {
                    "brightness": {
                        "name": "brightness",
                        "rect": [
                            100,
                            200,
                            300,
                            20
                        ],
                        "guiding_line_color": [
                            100,
                            100,
                            200
                        ],
                        "_type": "Slider",
                        "value": 0,
                        "min_value": 0,
                        "max_value": 1,
                        "color": [
                            0,
                            100,
                            0
                        ],
                        "handle_color": [
                            100,
                            0,
                            0
                        ],
                        "handle_radius": 10,
                        "direction": "horizontal",
                        "handle_shape": "circle",
                        "handle_length": 0
                    }
                }
            },
            "images": {
                "tabs": {},
                "input": {},
                "accessibility": {},
                "graphics": {},
                "audio": {},
                "gameplay": {}
            },
            "text_displays": {
                "tabs": {},
                "input": {},
                "accessibility": {},
                "graphics": {},
                "audio": {},
                "gameplay": {}
            }
        }
    ]
}